ssmi.py
ssmi_py-0.1.0.dist-info/LICENSE
ssmi_py-0.1.0.dist-info/METADATA
ssmi_py-0.1.0.dist-info/WHEEL
ssmi_py-0.1.0.dist-info/entry_points.txt
ssmi_py-0.1.0.dist-info/top_level.txt
ssmi_py-0.1.0.dist-info/RECORD
