Metadata-Version: 2.1
Name: ssmi-py
Version: 0.1.0
Summary: A simplified version of the output from the `nvidia-smi` command.
Home-page: https://github.com/simplified-nvidia-smi/py-ssmi
Author: Ben Elfner
License: MIT
Classifier: License :: OSI Approved :: MIT License
Classifier: Programming Language :: Python :: 3
Classifier: Programming Language :: Python :: 3 :: Only
Classifier: Programming Language :: Python :: 3.3
Classifier: Programming Language :: Python :: 3.4
Classifier: Programming Language :: Python :: 3.5
Classifier: Programming Language :: Python :: 3.6
Classifier: Programming Language :: Python :: 3.7
Classifier: Programming Language :: Python :: 3.8
Classifier: Programming Language :: Python :: 3.9
Classifier: Programming Language :: Python :: 3.10
Classifier: Programming Language :: Python :: 3.11
Classifier: Programming Language :: Python :: 3.12
Classifier: Programming Language :: Python :: Implementation :: CPython
Classifier: Operating System :: Unix
Classifier: Operating System :: Microsoft :: Windows
Classifier: Topic :: Utilities
Requires-Python: >=3.3
License-File: LICENSE
Provides-Extra: dev
Requires-Dist: twine ; extra == 'dev'
